vanturtlefan/__init__.py
vanturtlefan-1.0.0.dist-info/LICENSE
vanturtlefan-1.0.0.dist-info/METADATA
vanturtlefan-1.0.0.dist-info/WHEEL
vanturtlefan-1.0.0.dist-info/top_level.txt
vanturtlefan-1.0.0.dist-info/RECORD
