Metadata-Version: 2.1
Name: vanturtlefan
Version: 1.0.0
Summary: Library to interface with a VanTurtle analog fan controller over I2C
License: MIT
Requires-Python: >=3.5
License-File: LICENSE
